{
  "db_name": "PostgreSQL",
  "query": "SELECT version, updated_by_client FROM grocery_lists WHERE id = 'need-list-1'",
  "describe": {
    "columns": [
      {
        "ordinal": 0,
        "name": "version",
        "type_info": "Int4"
      },
      {
        "ordinal": 1,
        "name": "updated_by_client",
        "type_info": "Text"
      }
    ],
    "parameters": {
      "Left": []
    },
    "nullable": [
      false,
      true
    ]
  },
  "hash": "b0f156a0939ab6d83d142f1edfe17ef3547f083ceac0647f646457a495d6de01"
}
